django_bitgo/__init__.py
django_bitgo/admin.py
django_bitgo/apps.py
django_bitgo/client.py
django_bitgo/exceptions.py
django_bitgo/migrations/__init__.py
django_bitgo/models.py
django_bitgo/settings.py
django_bitgo/tests.py
django_bitgo/views.py
django_bitgo/wallets/address.py
django_bitgo-0.1.3.dist-info/LICENSE
django_bitgo-0.1.3.dist-info/WHEEL
django_bitgo-0.1.3.dist-info/METADATA
django_bitgo-0.1.3.dist-info/RECORD
