Metadata-Version: 2.1
Name: django-bitgo
Version: 0.1.3
Summary: Django app for bitGo
Home-page: https://github.com/panosangelopoulos/django_bitgo
License: MIT
Keywords: django,bitgo,django_bitgo
Author: panosangelopoulos
Author-email: panos.angelopoulos@outlook.com
Requires-Python: >=3.7.1,<4.0.0
Classifier: License :: OSI Approved :: MIT License
Classifier: Programming Language :: Python :: 3
Classifier: Programming Language :: Python :: 3.10
Classifier: Programming Language :: Python :: 3.8
Classifier: Programming Language :: Python :: 3.9
Requires-Dist: Django (>=3.2.14,<4.0.0)
Requires-Dist: requests (>=2.28.1,<3.0.0)
Project-URL: Repository, https://github.com/panosangelopoulos/django_bitgo
